eth_typing/__init__.py
eth_typing/abi.py
eth_typing/bls.py
eth_typing/discovery.py
eth_typing/encoding.py
eth_typing/enums.py
eth_typing/evm.py
eth_typing/exceptions.py
eth_typing/networks.py
eth_typing/py.typed
eth_typing-5.0.1.dist-info/LICENSE
eth_typing-5.0.1.dist-info/METADATA
eth_typing-5.0.1.dist-info/WHEEL
eth_typing-5.0.1.dist-info/top_level.txt
eth_typing-5.0.1.dist-info/RECORD
